LICENSE
MANIFEST.in
README.md
keywords.txt
requirements-dev.txt
requirements.txt
setup.cfg
setup.py
bip_utils/__init__.py
bip_utils/_version.py
bip_utils/addr/P2PKH_addr.py
bip_utils/addr/P2SH_addr.py
bip_utils/addr/P2TR_addr.py
bip_utils/addr/P2WPKH_addr.py
bip_utils/addr/__init__.py
bip_utils/addr/ada_byron_addr.py
bip_utils/addr/ada_shelley_addr.py
bip_utils/addr/addr_dec_utils.py
bip_utils/addr/addr_key_validator.py
bip_utils/addr/algo_addr.py
bip_utils/addr/aptos_addr.py
bip_utils/addr/atom_addr.py
bip_utils/addr/avax_addr.py
bip_utils/addr/bch_addr_converter.py
bip_utils/addr/egld_addr.py
bip_utils/addr/eos_addr.py
bip_utils/addr/ergo_addr.py
bip_utils/addr/eth_addr.py
bip_utils/addr/fil_addr.py
bip_utils/addr/iaddr_decoder.py
bip_utils/addr/iaddr_encoder.py
bip_utils/addr/icx_addr.py
bip_utils/addr/nano_addr.py
bip_utils/addr/near_addr.py
bip_utils/addr/neo_addr.py
bip_utils/addr/okex_addr.py
bip_utils/addr/one_addr.py
bip_utils/addr/sol_addr.py
bip_utils/addr/substrate_addr.py
bip_utils/addr/trx_addr.py
bip_utils/addr/xlm_addr.py
bip_utils/addr/xmr_addr.py
bip_utils/addr/xrp_addr.py
bip_utils/addr/xtz_addr.py
bip_utils/addr/zil_addr.py
bip_utils/algorand/__init__.py
bip_utils/algorand/mnemonic/__init__.py
bip_utils/algorand/mnemonic/algorand_entropy_generator.py
bip_utils/algorand/mnemonic/algorand_mnemonic.py
bip_utils/algorand/mnemonic/algorand_mnemonic_decoder.py
bip_utils/algorand/mnemonic/algorand_mnemonic_encoder.py
bip_utils/algorand/mnemonic/algorand_mnemonic_generator.py
bip_utils/algorand/mnemonic/algorand_mnemonic_utils.py
bip_utils/algorand/mnemonic/algorand_mnemonic_validator.py
bip_utils/algorand/mnemonic/algorand_seed_generator.py
bip_utils/base58/__init__.py
bip_utils/base58/base58.py
bip_utils/base58/base58_ex.py
bip_utils/base58/base58_xmr.py
bip_utils/bech32/__init__.py
bip_utils/bech32/bch_bech32.py
bip_utils/bech32/bech32.py
bip_utils/bech32/bech32_base.py
bip_utils/bech32/bech32_ex.py
bip_utils/bech32/segwit_bech32.py
open_aea_bip_utils.egg-info/PKG-INFO
open_aea_bip_utils.egg-info/SOURCES.txt
open_aea_bip_utils.egg-info/dependency_links.txt
open_aea_bip_utils.egg-info/requires.txt
open_aea_bip_utils.egg-info/top_level.txt
