Metadata-Version: 2.1
Name: open-aea-bip-utils
Version: 2.7.2
Summary: Generation of mnemonics, seeds, private/public keys and addresses for different types of cryptocurrencies
Home-page: https://github.com/ebellocchia/bip_utils
Download-URL: https://github.com/ebellocchia/bip_utils/archive/v2.7.2.tar.gz
Author: Emanuele Bellocchia
Author-email: ebellocchia@gmail.com
Maintainer: Emanuele Bellocchia
Maintainer-email: ebellocchia@gmail.com
License: MIT
Keywords: python,cryptography,ecdsa,ed25519,ed25519-blake2b,nist256p1,secp256k1,sr25519,wallet,hd-wallet,slip10,slip32,bip38,bip39,bip39-substrate,bip32,bip44,bip49,bip84,bip86,bip173,bip350,base58,ss58,bech32,bech32m,segwit,electrum,substrate,taproot,daedalus,byron,shelley,akash,algorand,aptos,atom,avalanche,avax,axelar,band protocol,binance chain,binance smart chain,bitcoin,bitcoin cash,bitcoinsv,bnb,cardano,cardano-byron,cardano-shelley,celo,certik,cosmos,dash,dogecoin,ecash,elrond,eos,ethere
Platform: any
Classifier: Programming Language :: Python :: 3.7
Classifier: Programming Language :: Python :: 3.8
Classifier: Programming Language :: Python :: 3.9
Classifier: Programming Language :: Python :: 3.10
Classifier: Programming Language :: Python :: 3.11
Classifier: Development Status :: 5 - Production/Stable
Classifier: License :: OSI Approved :: MIT License
Classifier: Operating System :: OS Independent
Classifier: Intended Audience :: Developers
Requires-Python: >=3.7
Provides-Extra: develop
License-File: LICENSE
